{
  "stat_id": "467",
  "stat_title": "Scrambling 20-30 yds (RTP Score)",
  "category": "Around the Green",
  "year": 2025,
  "tournament_id": "R2025011",
  "rows": [
    {
      "rank": 1,
      "player": "Will Chandler",
      "Avg RTP": "E",
      "Total Holes": "3",
      "Total RTP": "E"
    },
    {
      "rank": 1,
      "player": "Corey Conners",
      "Avg RTP": "E",
      "Total Holes": "1",
      "Total RTP": "E"
    },
    {
      "rank": 1,
      "player": "Ryan Fox",
      "Avg RTP": "E",
      "Total Holes": "5",
      "Total RTP": "E"
    },
    {
      "rank": 1,
      "player": "Joe Highsmith",
      "Avg RTP": "E",
      "Total Holes": "3",
      "Total RTP": "E"
    },
    {
      "rank": 1,
      "player": "Sungjae Im",
      "Avg RTP": "E",
      "Total Holes": "3",
      "Total RTP": "E"
    },
    {
      "rank": 1,
      "player": "Tom Kim",
      "Avg RTP": "E",
      "Total Holes": "2",
      "Total RTP": "E"
    },
    {
      "rank": 1,
      "player": "Robert MacIntyre",
      "Avg RTP": "E",
      "Total Holes": "2",
      "Total RTP": "E"
    },
    {
      "rank": 1,
      "player": "Scottie Scheffler",
      "Avg RTP": "E",
      "Total Holes": "1",
      "Total RTP": "E"
    },
    {
      "rank": 1,
      "player": "Jordan Spieth",
      "Avg RTP": "E",
      "Total Holes": "2",
      "Total RTP": "E"
    },
    {
      "rank": 1,
      "player": "Sahith Theegala",
      "Avg RTP": "E",
      "Total Holes": "2",
      "Total RTP": "E"
    },
    {
      "rank": 1,
      "player": "Davis Thompson",
      "Avg RTP": "E",
      "Total Holes": "3",
      "Total RTP": "E"
    },
    {
      "rank": 1,
      "player": "Sami Valimaki",
      "Avg RTP": "E",
      "Total Holes": "3",
      "Total RTP": "E"
    },
    {
      "rank": 1,
      "player": "Danny Walker",
      "Avg RTP": "E",
      "Total Holes": "2",
      "Total RTP": "E"
    },
    {
      "rank": 1,
      "player": "Cameron Young",
      "Avg RTP": "E",
      "Total Holes": "2",
      "Total RTP": "E"
    },
    {
      "rank": 15,
      "player": "Keegan Bradley",
      "Avg RTP": "+.143",
      "Total Holes": "7",
      "Total RTP": "+1.00"
    },
    {
      "rank": 16,
      "player": "Kurt Kitayama",
      "Avg RTP": "+.167",
      "Total Holes": "6",
      "Total RTP": "+1.00"
    },
    {
      "rank": 17,
      "player": "Tommy Fleetwood",
      "Avg RTP": "+.250",
      "Total Holes": "4",
      "Total RTP": "+1.00"
    },
    {
      "rank": 17,
      "player": "Chris Kirk",
      "Avg RTP": "+.250",
      "Total Holes": "4",
      "Total RTP": "+1.00"
    },
    {
      "rank": 17,
      "player": "Matt Kuchar",
      "Avg RTP": "+.250",
      "Total Holes": "4",
      "Total RTP": "+1.00"
    },
    {
      "rank": 17,
      "player": "Matt McCarty",
      "Avg RTP": "+.250",
      "Total Holes": "4",
      "Total RTP": "+1.00"
    },
    {
      "rank": 17,
      "player": "Max McGreevy",
      "Avg RTP": "+.250",
      "Total Holes": "4",
      "Total RTP": "+1.00"
    },
    {
      "rank": 17,
      "player": "J.T. Poston",
      "Avg RTP": "+.250",
      "Total Holes": "8",
      "Total RTP": "+2.00"
    },
    {
      "rank": 23,
      "player": "Jhonattan Vegas",
      "Avg RTP": "+.286",
      "Total Holes": "7",
      "Total RTP": "+2.00"
    },
    {
      "rank": 24,
      "player": "Emiliano Grillo",
      "Avg RTP": "+.333",
      "Total Holes": "6",
      "Total RTP": "+2.00"
    },
    {
      "rank": 24,
      "player": "Taylor Moore",
      "Avg RTP": "+.333",
      "Total Holes": "6",
      "Total RTP": "+2.00"
    },
    {
      "rank": 24,
      "player": "Jesper Svensson",
      "Avg RTP": "+.333",
      "Total Holes": "6",
      "Total RTP": "+2.00"
    },
    {
      "rank": 24,
      "player": "Carson Young",
      "Avg RTP": "+.333",
      "Total Holes": "3",
      "Total RTP": "+1.00"
    },
    {
      "rank": 28,
      "player": "Daniel Berger",
      "Avg RTP": "+.400",
      "Total Holes": "5",
      "Total RTP": "+2.00"
    },
    {
      "rank": 28,
      "player": "Harris English",
      "Avg RTP": "+.400",
      "Total Holes": "5",
      "Total RTP": "+2.00"
    },
    {
      "rank": 28,
      "player": "Min Woo Lee",
      "Avg RTP": "+.400",
      "Total Holes": "5",
      "Total RTP": "+2.00"
    },
    {
      "rank": 28,
      "player": "Mac Meissner",
      "Avg RTP": "+.400",
      "Total Holes": "5",
      "Total RTP": "+2.00"
    },
    {
      "rank": 28,
      "player": "Camilo Villegas",
      "Avg RTP": "+.400",
      "Total Holes": "10",
      "Total RTP": "+4.00"
    },
    {
      "rank": 33,
      "player": "Xander Schauffele",
      "Avg RTP": "+.444",
      "Total Holes": "9",
      "Total RTP": "+4.00"
    },
    {
      "rank": 34,
      "player": "Ryan Gerard",
      "Avg RTP": "+.500",
      "Total Holes": "4",
      "Total RTP": "+2.00"
    },
    {
      "rank": 34,
      "player": "Charley Hoffman",
      "Avg RTP": "+.500",
      "Total Holes": "4",
      "Total RTP": "+2.00"
    },
    {
      "rank": 34,
      "player": "Stephan Jaeger",
      "Avg RTP": "+.500",
      "Total Holes": "2",
      "Total RTP": "+1.00"
    },
    {
      "rank": 34,
      "player": "Shane Lowry",
      "Avg RTP": "+.500",
      "Total Holes": "4",
      "Total RTP": "+2.00"
    },
    {
      "rank": 34,
      "player": "Davis Riley",
      "Avg RTP": "+.500",
      "Total Holes": "2",
      "Total RTP": "+1.00"
    },
    {
      "rank": 34,
      "player": "Sam Ryder",
      "Avg RTP": "+.500",
      "Total Holes": "6",
      "Total RTP": "+3.00"
    },
    {
      "rank": 34,
      "player": "Isaiah Salinda",
      "Avg RTP": "+.500",
      "Total Holes": "6",
      "Total RTP": "+3.00"
    },
    {
      "rank": 34,
      "player": "Alex Smalley",
      "Avg RTP": "+.500",
      "Total Holes": "2",
      "Total RTP": "+1.00"
    },
    {
      "rank": 34,
      "player": "Hayden Springer",
      "Avg RTP": "+.500",
      "Total Holes": "6",
      "Total RTP": "+3.00"
    },
    {
      "rank": 34,
      "player": "Justin Thomas",
      "Avg RTP": "+.500",
      "Total Holes": "6",
      "Total RTP": "+3.00"
    },
    {
      "rank": 34,
      "player": "Will Zalatoris",
      "Avg RTP": "+.500",
      "Total Holes": "4",
      "Total RTP": "+2.00"
    },
    {
      "rank": 45,
      "player": "Joel Dahmen",
      "Avg RTP": "+.600",
      "Total Holes": "5",
      "Total RTP": "+3.00"
    },
    {
      "rank": 45,
      "player": "Austin Eckroat",
      "Avg RTP": "+.600",
      "Total Holes": "5",
      "Total RTP": "+3.00"
    },
    {
      "rank": 45,
      "player": "Rickie Fowler",
      "Avg RTP": "+.600",
      "Total Holes": "5",
      "Total RTP": "+3.00"
    },
    {
      "rank": 45,
      "player": "Denny McCarthy",
      "Avg RTP": "+.600",
      "Total Holes": "5",
      "Total RTP": "+3.00"
    },
    {
      "rank": 45,
      "player": "Taylor Pendrith",
      "Avg RTP": "+.600",
      "Total Holes": "5",
      "Total RTP": "+3.00"
    },
    {
      "rank": 50,
      "player": "Byeong Hun An",
      "Avg RTP": "+.667",
      "Total Holes": "3",
      "Total RTP": "+2.00"
    },
    {
      "rank": 50,
      "player": "Patrick Cantlay",
      "Avg RTP": "+.667",
      "Total Holes": "3",
      "Total RTP": "+2.00"
    },
    {
      "rank": 50,
      "player": "Russell Henley",
      "Avg RTP": "+.667",
      "Total Holes": "3",
      "Total RTP": "+2.00"
    },
    {
      "rank": 50,
      "player": "Si Woo Kim",
      "Avg RTP": "+.667",
      "Total Holes": "3",
      "Total RTP": "+2.00"
    },
    {
      "rank": 50,
      "player": "Matthieu Pavon",
      "Avg RTP": "+.667",
      "Total Holes": "6",
      "Total RTP": "+4.00"
    },
    {
      "rank": 50,
      "player": "J.J. Spaun",
      "Avg RTP": "+.667",
      "Total Holes": "3",
      "Total RTP": "+2.00"
    },
    {
      "rank": 56,
      "player": "Beau Hossler",
      "Avg RTP": "+.714",
      "Total Holes": "7",
      "Total RTP": "+5.00"
    },
    {
      "rank": 57,
      "player": "Bud Cauley",
      "Avg RTP": "+.750",
      "Total Holes": "4",
      "Total RTP": "+3.00"
    },
    {
      "rank": 57,
      "player": "Justin Lower",
      "Avg RTP": "+.750",
      "Total Holes": "4",
      "Total RTP": "+3.00"
    },
    {
      "rank": 57,
      "player": "Rory McIlroy",
      "Avg RTP": "+.750",
      "Total Holes": "4",
      "Total RTP": "+3.00"
    },
    {
      "rank": 60,
      "player": "Billy Horschel",
      "Avg RTP": "+.800",
      "Total Holes": "5",
      "Total RTP": "+4.00"
    },
    {
      "rank": 60,
      "player": "Jake Knapp",
      "Avg RTP": "+.800",
      "Total Holes": "5",
      "Total RTP": "+4.00"
    },
    {
      "rank": 60,
      "player": "C.T. Pan",
      "Avg RTP": "+.800",
      "Total Holes": "5",
      "Total RTP": "+4.00"
    },
    {
      "rank": 63,
      "player": "Lucas Glover",
      "Avg RTP": "+.833",
      "Total Holes": "6",
      "Total RTP": "+5.00"
    },
    {
      "rank": 64,
      "player": "Akshay Bhatia",
      "Avg RTP": "+1.000",
      "Total Holes": "2",
      "Total RTP": "+2.00"
    },
    {
      "rank": 64,
      "player": "Jacob Bridgeman",
      "Avg RTP": "+1.000",
      "Total Holes": "1",
      "Total RTP": "+1.00"
    },
    {
      "rank": 64,
      "player": "Tom Hoge",
      "Avg RTP": "+1.000",
      "Total Holes": "1",
      "Total RTP": "+1.00"
    },
    {
      "rank": 64,
      "player": "Collin Morikawa",
      "Avg RTP": "+1.000",
      "Total Holes": "1",
      "Total RTP": "+1.00"
    },
    {
      "rank": 64,
      "player": "Chandler Phillips",
      "Avg RTP": "+1.000",
      "Total Holes": "5",
      "Total RTP": "+5.00"
    },
    {
      "rank": 64,
      "player": "Aaron Rai",
      "Avg RTP": "+1.000",
      "Total Holes": "2",
      "Total RTP": "+2.00"
    },
    {
      "rank": 64,
      "player": "Sepp Straka",
      "Avg RTP": "+1.000",
      "Total Holes": "1",
      "Total RTP": "+1.00"
    },
    {
      "rank": 71,
      "player": "Rico Hoey",
      "Avg RTP": "+1.250",
      "Total Holes": "4",
      "Total RTP": "+5.00"
    },
    {
      "rank": 72,
      "player": "Trey Mullinax",
      "Avg RTP": "+1.500",
      "Total Holes": "2",
      "Total RTP": "+3.00"
    }
  ]
}