{
  "stat_id": "484",
  "year": 2026,
  "category": "Putting",
  "stat_title": "Putting Inside 10\u2019",
  "rows": [
    {
      "rank": 1,
      "player": "Matt Kuchar",
      "% Made": "91.91%",
      "Attempts": "408",
      "Putts made": "375"
    },
    {
      "rank": 2,
      "player": "Rickie Fowler",
      "% Made": "91.11%",
      "Attempts": "787",
      "Putts made": "717"
    },
    {
      "rank": 3,
      "player": "Nicolai H\u00f8jgaard",
      "% Made": "91.10%",
      "Attempts": "775",
      "Putts made": "706"
    },
    {
      "rank": 4,
      "player": "Adrien Dumont de Chassart",
      "% Made": "91.05%",
      "Attempts": "581",
      "Putts made": "529"
    },
    {
      "rank": 5,
      "player": "Ben Griffin",
      "% Made": "90.90%",
      "Attempts": "857",
      "Putts made": "779"
    },
    {
      "rank": 6,
      "player": "Jimmy Stanger",
      "% Made": "90.89%",
      "Attempts": "417",
      "Putts made": "379"
    },
    {
      "rank": 7,
      "player": "Vince Whaley",
      "% Made": "90.77%",
      "Attempts": "531",
      "Putts made": "482"
    },
    {
      "rank": 8,
      "player": "Karl Vilips",
      "% Made": "90.69%",
      "Attempts": "591",
      "Putts made": "536"
    },
    {
      "rank": 9,
      "player": "Taylor Moore",
      "% Made": "90.48%",
      "Attempts": "662",
      "Putts made": "599"
    },
    {
      "rank": 10,
      "player": "Jacob Bridgeman",
      "% Made": "90.28%",
      "Attempts": "772",
      "Putts made": "697"
    },
    {
      "rank": 11,
      "player": "Lanto Griffin",
      "% Made": "90.16%",
      "Attempts": "315",
      "Putts made": "284"
    },
    {
      "rank": 12,
      "player": "Steven Fisk",
      "% Made": "90.10%",
      "Attempts": "778",
      "Putts made": "701"
    },
    {
      "rank": 13,
      "player": "Eric Cole",
      "% Made": "90.07%",
      "Attempts": "695",
      "Putts made": "626"
    },
    {
      "rank": 14,
      "player": "Ricky Castillo",
      "% Made": "90.06%",
      "Attempts": "775",
      "Putts made": "698"
    },
    {
      "rank": 15,
      "player": "J.T. Poston",
      "% Made": "90.00%",
      "Attempts": "760",
      "Putts made": "684"
    },
    {
      "rank": 16,
      "player": "Rasmus Neergaard-Petersen",
      "% Made": "89.95%",
      "Attempts": "567",
      "Putts made": "510"
    },
    {
      "rank": 17,
      "player": "Sam Ryder",
      "% Made": "89.94%",
      "Attempts": "507",
      "Putts made": "456"
    },
    {
      "rank": 18,
      "player": "Beau Hossler",
      "% Made": "89.89%",
      "Attempts": "455",
      "Putts made": "409"
    },
    {
      "rank": 19,
      "player": "Adrien Saddier",
      "% Made": "89.86%",
      "Attempts": "562",
      "Putts made": "505"
    },
    {
      "rank": 20,
      "player": "Kensei Hirata",
      "% Made": "89.85%",
      "Attempts": "581",
      "Putts made": "522"
    },
    {
      "rank": 21,
      "player": "Mac Meissner",
      "% Made": "89.75%",
      "Attempts": "693",
      "Putts made": "622"
    },
    {
      "rank": 22,
      "player": "Alex Noren",
      "% Made": "89.70%",
      "Attempts": "689",
      "Putts made": "618"
    },
    {
      "rank": 23,
      "player": "Sudarshan Yellamaraju",
      "% Made": "89.68%",
      "Attempts": "785",
      "Putts made": "704"
    },
    {
      "rank": 24,
      "player": "Nick Dunlap",
      "% Made": "89.67%",
      "Attempts": "426",
      "Putts made": "382"
    },
    {
      "rank": 25,
      "player": "S.H. Kim",
      "% Made": "89.61%",
      "Attempts": "491",
      "Putts made": "440"
    },
    {
      "rank": 26,
      "player": "John VanDerLaan",
      "% Made": "89.60%",
      "Attempts": "548",
      "Putts made": "491"
    },
    {
      "rank": 27,
      "player": "Thorbj\u00f8rn Olesen",
      "% Made": "89.56%",
      "Attempts": "498",
      "Putts made": "446"
    },
    {
      "rank": 28,
      "player": "Pontus Nyholm",
      "% Made": "89.55%",
      "Attempts": "469",
      "Putts made": "420"
    },
    {
      "rank": 29,
      "player": "Brandt Snedeker",
      "% Made": "89.49%",
      "Attempts": "390",
      "Putts made": "349"
    },
    {
      "rank": 30,
      "player": "Rafael Campos",
      "% Made": "89.47%",
      "Attempts": "361",
      "Putts made": "323"
    },
    {
      "rank": 31,
      "player": "Chad Ramey",
      "% Made": "89.44%",
      "Attempts": "720",
      "Putts made": "644"
    },
    {
      "rank": 32,
      "player": "Sam Burns",
      "% Made": "89.41%",
      "Attempts": "642",
      "Putts made": "574"
    },
    {
      "rank": 33,
      "player": "Christiaan Bezuidenhout",
      "% Made": "89.38%",
      "Attempts": "706",
      "Putts made": "631"
    },
    {
      "rank": 34,
      "player": "A.J. Ewart",
      "% Made": "89.34%",
      "Attempts": "666",
      "Putts made": "595"
    },
    {
      "rank": 35,
      "player": "Robert MacIntyre",
      "% Made": "89.31%",
      "Attempts": "711",
      "Putts made": "635"
    },
    {
      "rank": 35,
      "player": "Alex Smalley",
      "% Made": "89.31%",
      "Attempts": "907",
      "Putts made": "810"
    },
    {
      "rank": 37,
      "player": "Mackenzie Hughes",
      "% Made": "89.29%",
      "Attempts": "691",
      "Putts made": "617"
    },
    {
      "rank": 38,
      "player": "Denny McCarthy",
      "% Made": "89.27%",
      "Attempts": "867",
      "Putts made": "774"
    },
    {
      "rank": 39,
      "player": "Michael Thorbjornsen",
      "% Made": "89.21%",
      "Attempts": "806",
      "Putts made": "719"
    },
    {
      "rank": 40,
      "player": "Tommy Fleetwood",
      "% Made": "89.08%",
      "Attempts": "632",
      "Putts made": "563"
    },
    {
      "rank": 41,
      "player": "Zecheng Dou",
      "% Made": "89.06%",
      "Attempts": "631",
      "Putts made": "562"
    },
    {
      "rank": 42,
      "player": "Justin Lower",
      "% Made": "89.05%",
      "Attempts": "402",
      "Putts made": "358"
    },
    {
      "rank": 43,
      "player": "Bud Cauley",
      "% Made": "89.04%",
      "Attempts": "876",
      "Putts made": "780"
    },
    {
      "rank": 44,
      "player": "Max Homa",
      "% Made": "89.01%",
      "Attempts": "755",
      "Putts made": "672"
    },
    {
      "rank": 44,
      "player": "Kevin Roy",
      "% Made": "89.01%",
      "Attempts": "728",
      "Putts made": "648"
    },
    {
      "rank": 44,
      "player": "Erik van Rooyen",
      "% Made": "89.01%",
      "Attempts": "564",
      "Putts made": "502"
    },
    {
      "rank": 47,
      "player": "Russell Henley",
      "% Made": "88.98%",
      "Attempts": "644",
      "Putts made": "573"
    },
    {
      "rank": 47,
      "player": "Michael Kim",
      "% Made": "88.98%",
      "Attempts": "880",
      "Putts made": "783"
    },
    {
      "rank": 47,
      "player": "Neal Shipley",
      "% Made": "88.98%",
      "Attempts": "490",
      "Putts made": "436"
    },
    {
      "rank": 50,
      "player": "Andrew Putnam",
      "% Made": "88.94%",
      "Attempts": "823",
      "Putts made": "732"
    },
    {
      "rank": 51,
      "player": "Chris Gotterup",
      "% Made": "88.92%",
      "Attempts": "821",
      "Putts made": "730"
    },
    {
      "rank": 52,
      "player": "Tom Hoge",
      "% Made": "88.90%",
      "Attempts": "928",
      "Putts made": "825"
    },
    {
      "rank": 53,
      "player": "Davis Chatfield",
      "% Made": "88.89%",
      "Attempts": "423",
      "Putts made": "376"
    },
    {
      "rank": 54,
      "player": "Harry Hall",
      "% Made": "88.87%",
      "Attempts": "728",
      "Putts made": "647"
    },
    {
      "rank": 54,
      "player": "Garrick Higgo",
      "% Made": "88.87%",
      "Attempts": "764",
      "Putts made": "679"
    },
    {
      "rank": 56,
      "player": "Rico Hoey",
      "% Made": "88.85%",
      "Attempts": "960",
      "Putts made": "853"
    },
    {
      "rank": 57,
      "player": "Matthieu Pavon",
      "% Made": "88.82%",
      "Attempts": "626",
      "Putts made": "556"
    },
    {
      "rank": 58,
      "player": "Shane Lowry",
      "% Made": "88.77%",
      "Attempts": "579",
      "Putts made": "514"
    },
    {
      "rank": 59,
      "player": "Patrick Rodgers",
      "% Made": "88.76%",
      "Attempts": "1,059",
      "Putts made": "940"
    },
    {
      "rank": 59,
      "player": "Austin Smotherman",
      "% Made": "88.76%",
      "Attempts": "765",
      "Putts made": "679"
    },
    {
      "rank": 61,
      "player": "Seamus Power",
      "% Made": "88.69%",
      "Attempts": "681",
      "Putts made": "604"
    },
    {
      "rank": 62,
      "player": "Xander Schauffele",
      "% Made": "88.66%",
      "Attempts": "688",
      "Putts made": "610"
    },
    {
      "rank": 63,
      "player": "Lee Hodges",
      "% Made": "88.65%",
      "Attempts": "617",
      "Putts made": "547"
    },
    {
      "rank": 64,
      "player": "Chandler Blanchet",
      "% Made": "88.64%",
      "Attempts": "713",
      "Putts made": "632"
    },
    {
      "rank": 65,
      "player": "Davis Riley",
      "% Made": "88.63%",
      "Attempts": "563",
      "Putts made": "499"
    },
    {
      "rank": 66,
      "player": "Sungjae Im",
      "% Made": "88.60%",
      "Attempts": "570",
      "Putts made": "505"
    },
    {
      "rank": 66,
      "player": "Matt Wallace",
      "% Made": "88.60%",
      "Attempts": "614",
      "Putts made": "544"
    },
    {
      "rank": 68,
      "player": "William Mouw",
      "% Made": "88.49%",
      "Attempts": "617",
      "Putts made": "546"
    },
    {
      "rank": 69,
      "player": "Takumi Kanaya",
      "% Made": "88.47%",
      "Attempts": "720",
      "Putts made": "637"
    },
    {
      "rank": 70,
      "player": "Harris English",
      "% Made": "88.46%",
      "Attempts": "780",
      "Putts made": "690"
    },
    {
      "rank": 71,
      "player": "Akshay Bhatia",
      "% Made": "88.44%",
      "Attempts": "718",
      "Putts made": "635"
    },
    {
      "rank": 72,
      "player": "Max Greyserman",
      "% Made": "88.42%",
      "Attempts": "708",
      "Putts made": "626"
    },
    {
      "rank": 72,
      "player": "Brian Harman",
      "% Made": "88.42%",
      "Attempts": "872",
      "Putts made": "771"
    },
    {
      "rank": 74,
      "player": "Min Woo Lee",
      "% Made": "88.41%",
      "Attempts": "768",
      "Putts made": "679"
    },
    {
      "rank": 75,
      "player": "Nico Echavarria",
      "% Made": "88.38%",
      "Attempts": "783",
      "Putts made": "692"
    },
    {
      "rank": 76,
      "player": "Christo Lamprecht",
      "% Made": "88.37%",
      "Attempts": "447",
      "Putts made": "395"
    },
    {
      "rank": 77,
      "player": "Cameron Young",
      "% Made": "88.35%",
      "Attempts": "695",
      "Putts made": "614"
    },
    {
      "rank": 78,
      "player": "Peter Malnati",
      "% Made": "88.32%",
      "Attempts": "471",
      "Putts made": "416"
    },
    {
      "rank": 79,
      "player": "Keith Mitchell",
      "% Made": "88.22%",
      "Attempts": "908",
      "Putts made": "801"
    },
    {
      "rank": 79,
      "player": "Jesper Svensson",
      "% Made": "88.22%",
      "Attempts": "331",
      "Putts made": "292"
    },
    {
      "rank": 81,
      "player": "Pierceson Coody",
      "% Made": "88.16%",
      "Attempts": "946",
      "Putts made": "834"
    },
    {
      "rank": 81,
      "player": "Jake Knapp",
      "% Made": "88.16%",
      "Attempts": "515",
      "Putts made": "454"
    },
    {
      "rank": 83,
      "player": "Scottie Scheffler",
      "% Made": "88.14%",
      "Attempts": "683",
      "Putts made": "602"
    },
    {
      "rank": 84,
      "player": "Ludvig \u00c5berg",
      "% Made": "88.13%",
      "Attempts": "674",
      "Putts made": "594"
    },
    {
      "rank": 84,
      "player": "John Parry",
      "% Made": "88.13%",
      "Attempts": "800",
      "Putts made": "705"
    },
    {
      "rank": 86,
      "player": "Chandler Phillips",
      "% Made": "88.10%",
      "Attempts": "605",
      "Putts made": "533"
    },
    {
      "rank": 87,
      "player": "Jordan Spieth",
      "% Made": "88.02%",
      "Attempts": "918",
      "Putts made": "808"
    },
    {
      "rank": 88,
      "player": "Stephan Jaeger",
      "% Made": "88.00%",
      "Attempts": "750",
      "Putts made": "660"
    },
    {
      "rank": 88,
      "player": "Kurt Kitayama",
      "% Made": "88.00%",
      "Attempts": "800",
      "Putts made": "704"
    },
    {
      "rank": 88,
      "player": "Patton Kizzire",
      "% Made": "88.00%",
      "Attempts": "500",
      "Putts made": "440"
    },
    {
      "rank": 91,
      "player": "Ryan Gerard",
      "% Made": "87.97%",
      "Attempts": "898",
      "Putts made": "790"
    },
    {
      "rank": 91,
      "player": "Kevin Streelman",
      "% Made": "87.97%",
      "Attempts": "399",
      "Putts made": "351"
    },
    {
      "rank": 93,
      "player": "Nick Taylor",
      "% Made": "87.94%",
      "Attempts": "887",
      "Putts made": "780"
    },
    {
      "rank": 94,
      "player": "Hideki Matsuyama",
      "% Made": "87.91%",
      "Attempts": "877",
      "Putts made": "771"
    },
    {
      "rank": 95,
      "player": "Zach Bauchou",
      "% Made": "87.89%",
      "Attempts": "743",
      "Putts made": "653"
    },
    {
      "rank": 96,
      "player": "Marco Penge",
      "% Made": "87.85%",
      "Attempts": "543",
      "Putts made": "477"
    },
    {
      "rank": 96,
      "player": "Sahith Theegala",
      "% Made": "87.85%",
      "Attempts": "1,004",
      "Putts made": "882"
    },
    {
      "rank": 98,
      "player": "Doug Ghim",
      "% Made": "87.84%",
      "Attempts": "592",
      "Putts made": "520"
    },
    {
      "rank": 99,
      "player": "Viktor Hovland",
      "% Made": "87.82%",
      "Attempts": "665",
      "Putts made": "584"
    },
    {
      "rank": 100,
      "player": "Daniel Berger",
      "% Made": "87.81%",
      "Attempts": "812",
      "Putts made": "713"
    },
    {
      "rank": 100,
      "player": "Justin Rose",
      "% Made": "87.81%",
      "Attempts": "517",
      "Putts made": "454"
    },
    {
      "rank": 102,
      "player": "David Lipsky",
      "% Made": "87.80%",
      "Attempts": "541",
      "Putts made": "475"
    },
    {
      "rank": 103,
      "player": "Patrick Cantlay",
      "% Made": "87.79%",
      "Attempts": "614",
      "Putts made": "539"
    },
    {
      "rank": 103,
      "player": "Matti Schmid",
      "% Made": "87.79%",
      "Attempts": "745",
      "Putts made": "654"
    },
    {
      "rank": 105,
      "player": "Davis Thompson",
      "% Made": "87.77%",
      "Attempts": "638",
      "Putts made": "560"
    },
    {
      "rank": 106,
      "player": "Gary Woodland",
      "% Made": "87.76%",
      "Attempts": "711",
      "Putts made": "624"
    },
    {
      "rank": 107,
      "player": "Adam Scott",
      "% Made": "87.75%",
      "Attempts": "653",
      "Putts made": "573"
    },
    {
      "rank": 108,
      "player": "Si Woo Kim",
      "% Made": "87.66%",
      "Attempts": "989",
      "Putts made": "867"
    },
    {
      "rank": 109,
      "player": "Brian Campbell",
      "% Made": "87.64%",
      "Attempts": "712",
      "Putts made": "624"
    },
    {
      "rank": 109,
      "player": "Max McGreevy",
      "% Made": "87.64%",
      "Attempts": "817",
      "Putts made": "716"
    },
    {
      "rank": 109,
      "player": "Jackson Suber",
      "% Made": "87.64%",
      "Attempts": "518",
      "Putts made": "454"
    },
    {
      "rank": 112,
      "player": "Ryan Fox",
      "% Made": "87.56%",
      "Attempts": "627",
      "Putts made": "549"
    },
    {
      "rank": 112,
      "player": "Jordan Smith",
      "% Made": "87.56%",
      "Attempts": "844",
      "Putts made": "739"
    },
    {
      "rank": 114,
      "player": "Aaron Rai",
      "% Made": "87.52%",
      "Attempts": "513",
      "Putts made": "449"
    },
    {
      "rank": 114,
      "player": "Kristoffer Reitan",
      "% Made": "87.52%",
      "Attempts": "689",
      "Putts made": "603"
    },
    {
      "rank": 116,
      "player": "Tony Finau",
      "% Made": "87.50%",
      "Attempts": "856",
      "Putts made": "749"
    },
    {
      "rank": 117,
      "player": "Tom Kim",
      "% Made": "87.47%",
      "Attempts": "798",
      "Putts made": "698"
    },
    {
      "rank": 118,
      "player": "Billy Horschel",
      "% Made": "87.46%",
      "Attempts": "869",
      "Putts made": "760"
    },
    {
      "rank": 119,
      "player": "Maverick McNealy",
      "% Made": "87.44%",
      "Attempts": "820",
      "Putts made": "717"
    },
    {
      "rank": 120,
      "player": "Cam Davis",
      "% Made": "87.42%",
      "Attempts": "453",
      "Putts made": "396"
    },
    {
      "rank": 121,
      "player": "Matt McCarty",
      "% Made": "87.40%",
      "Attempts": "913",
      "Putts made": "798"
    },
    {
      "rank": 122,
      "player": "Matt Fitzpatrick",
      "% Made": "87.39%",
      "Attempts": "706",
      "Putts made": "617"
    },
    {
      "rank": 123,
      "player": "Rasmus H\u00f8jgaard",
      "% Made": "87.31%",
      "Attempts": "670",
      "Putts made": "585"
    },
    {
      "rank": 124,
      "player": "Adam Schenk",
      "% Made": "87.27%",
      "Attempts": "746",
      "Putts made": "651"
    },
    {
      "rank": 125,
      "player": "Ryo Hisatsune",
      "% Made": "87.20%",
      "Attempts": "1,109",
      "Putts made": "967"
    },
    {
      "rank": 125,
      "player": "Danny Walker",
      "% Made": "87.20%",
      "Attempts": "664",
      "Putts made": "579"
    },
    {
      "rank": 127,
      "player": "J.J. Spaun",
      "% Made": "87.19%",
      "Attempts": "773",
      "Putts made": "674"
    },
    {
      "rank": 128,
      "player": "Corey Conners",
      "% Made": "87.16%",
      "Attempts": "779",
      "Putts made": "679"
    },
    {
      "rank": 128,
      "player": "Sami Valimaki",
      "% Made": "87.16%",
      "Attempts": "592",
      "Putts made": "516"
    },
    {
      "rank": 130,
      "player": "Hank Lebioda",
      "% Made": "87.15%",
      "Attempts": "599",
      "Putts made": "522"
    },
    {
      "rank": 130,
      "player": "Dylan Wu",
      "% Made": "87.15%",
      "Attempts": "467",
      "Putts made": "407"
    },
    {
      "rank": 132,
      "player": "David Ford",
      "% Made": "87.14%",
      "Attempts": "420",
      "Putts made": "366"
    },
    {
      "rank": 133,
      "player": "Jason Day",
      "% Made": "87.13%",
      "Attempts": "684",
      "Putts made": "596"
    },
    {
      "rank": 133,
      "player": "Haotong Li",
      "% Made": "87.13%",
      "Attempts": "614",
      "Putts made": "535"
    },
    {
      "rank": 133,
      "player": "Sepp Straka",
      "% Made": "87.13%",
      "Attempts": "684",
      "Putts made": "596"
    },
    {
      "rank": 136,
      "player": "Emiliano Grillo",
      "% Made": "87.08%",
      "Attempts": "743",
      "Putts made": "647"
    },
    {
      "rank": 137,
      "player": "Kris Ventura",
      "% Made": "87.06%",
      "Attempts": "340",
      "Putts made": "296"
    },
    {
      "rank": 138,
      "player": "Patrick Fishburn",
      "% Made": "87.02%",
      "Attempts": "470",
      "Putts made": "409"
    },
    {
      "rank": 139,
      "player": "Justin Thomas",
      "% Made": "86.94%",
      "Attempts": "559",
      "Putts made": "486"
    },
    {
      "rank": 140,
      "player": "Lucas Glover",
      "% Made": "86.93%",
      "Attempts": "658",
      "Putts made": "572"
    },
    {
      "rank": 141,
      "player": "Sam Stevens",
      "% Made": "86.83%",
      "Attempts": "957",
      "Putts made": "831"
    },
    {
      "rank": 142,
      "player": "Joel Dahmen",
      "% Made": "86.72%",
      "Attempts": "625",
      "Putts made": "542"
    },
    {
      "rank": 143,
      "player": "Gordon Sargent",
      "% Made": "86.69%",
      "Attempts": "338",
      "Putts made": "293"
    },
    {
      "rank": 144,
      "player": "Wyndham Clark",
      "% Made": "86.54%",
      "Attempts": "654",
      "Putts made": "566"
    },
    {
      "rank": 145,
      "player": "Luke Clanton",
      "% Made": "86.41%",
      "Attempts": "515",
      "Putts made": "445"
    },
    {
      "rank": 145,
      "player": "Mark Hubbard",
      "% Made": "86.41%",
      "Attempts": "677",
      "Putts made": "585"
    },
    {
      "rank": 147,
      "player": "Taylor Pendrith",
      "% Made": "86.34%",
      "Attempts": "871",
      "Putts made": "752"
    },
    {
      "rank": 148,
      "player": "Dan Brown",
      "% Made": "86.32%",
      "Attempts": "585",
      "Putts made": "505"
    },
    {
      "rank": 149,
      "player": "Austin Eckroat",
      "% Made": "86.25%",
      "Attempts": "618",
      "Putts made": "533"
    },
    {
      "rank": 150,
      "player": "Brice Garnett",
      "% Made": "86.21%",
      "Attempts": "522",
      "Putts made": "450"
    },
    {
      "rank": 151,
      "player": "Jhonattan Vegas",
      "% Made": "86.14%",
      "Attempts": "765",
      "Putts made": "659"
    },
    {
      "rank": 152,
      "player": "Jeffrey Kang",
      "% Made": "86.12%",
      "Attempts": "533",
      "Putts made": "459"
    },
    {
      "rank": 152,
      "player": "Collin Morikawa",
      "% Made": "86.12%",
      "Attempts": "569",
      "Putts made": "490"
    },
    {
      "rank": 154,
      "player": "Keegan Bradley",
      "% Made": "86.11%",
      "Attempts": "720",
      "Putts made": "620"
    },
    {
      "rank": 155,
      "player": "Chris Kirk",
      "% Made": "86.04%",
      "Attempts": "702",
      "Putts made": "604"
    },
    {
      "rank": 156,
      "player": "Joe Highsmith",
      "% Made": "85.92%",
      "Attempts": "838",
      "Putts made": "720"
    },
    {
      "rank": 157,
      "player": "Adam Svensson",
      "% Made": "85.86%",
      "Attempts": "495",
      "Putts made": "425"
    },
    {
      "rank": 158,
      "player": "Johnny Keefer",
      "% Made": "85.53%",
      "Attempts": "836",
      "Putts made": "715"
    },
    {
      "rank": 159,
      "player": "Andrew Novak",
      "% Made": "85.46%",
      "Attempts": "908",
      "Putts made": "776"
    },
    {
      "rank": 160,
      "player": "Brooks Koepka",
      "% Made": "85.29%",
      "Attempts": "578",
      "Putts made": "493"
    },
    {
      "rank": 161,
      "player": "Michael Brennan",
      "% Made": "85.21%",
      "Attempts": "683",
      "Putts made": "582"
    },
    {
      "rank": 162,
      "player": "Aldrich Potgieter",
      "% Made": "85.15%",
      "Attempts": "680",
      "Putts made": "579"
    },
    {
      "rank": 163,
      "player": "Alejandro Tosti",
      "% Made": "84.92%",
      "Attempts": "431",
      "Putts made": "366"
    },
    {
      "rank": 164,
      "player": "Kevin Yu",
      "% Made": "84.12%",
      "Attempts": "617",
      "Putts made": "519"
    },
    {
      "rank": 165,
      "player": "Marcelo Rozo",
      "% Made": "82.60%",
      "Attempts": "431",
      "Putts made": "356"
    }
  ]
}