{
  "stat_id": "264",
  "stat_title": "Late Round 3 Scoring Average",
  "category": "Scoring",
  "year": 2024,
  "tournament_id": "R2024011",
  "rows": [
    {
      "rank": 1,
      "player": "Brian Harman",
      "Avg": "64.00",
      "Total Strokes": "64",
      "Total Rounds": "1"
    },
    {
      "rank": 2,
      "player": "Xander Schauffele",
      "Avg": "65.00",
      "Total Strokes": "65",
      "Total Rounds": "1"
    },
    {
      "rank": 3,
      "player": "Doug Ghim",
      "Avg": "66.00",
      "Total Strokes": "66",
      "Total Rounds": "1"
    },
    {
      "rank": 4,
      "player": "Ludvig \u00c5berg",
      "Avg": "67.00",
      "Total Strokes": "67",
      "Total Rounds": "1"
    },
    {
      "rank": 4,
      "player": "Nate Lashley",
      "Avg": "67.00",
      "Total Strokes": "67",
      "Total Rounds": "1"
    },
    {
      "rank": 4,
      "player": "Sahith Theegala",
      "Avg": "67.00",
      "Total Strokes": "67",
      "Total Rounds": "1"
    },
    {
      "rank": 7,
      "player": "Christiaan Bezuidenhout",
      "Avg": "68.00",
      "Total Strokes": "68",
      "Total Rounds": "1"
    },
    {
      "rank": 7,
      "player": "Austin Eckroat",
      "Avg": "68.00",
      "Total Strokes": "68",
      "Total Rounds": "1"
    },
    {
      "rank": 7,
      "player": "Matt Fitzpatrick",
      "Avg": "68.00",
      "Total Strokes": "68",
      "Total Rounds": "1"
    },
    {
      "rank": 7,
      "player": "Hideki Matsuyama",
      "Avg": "68.00",
      "Total Strokes": "68",
      "Total Rounds": "1"
    },
    {
      "rank": 7,
      "player": "Maverick McNealy",
      "Avg": "68.00",
      "Total Strokes": "68",
      "Total Rounds": "1"
    },
    {
      "rank": 7,
      "player": "Taylor Montgomery",
      "Avg": "68.00",
      "Total Strokes": "68",
      "Total Rounds": "1"
    },
    {
      "rank": 7,
      "player": "Matt NeSmith",
      "Avg": "68.00",
      "Total Strokes": "68",
      "Total Rounds": "1"
    },
    {
      "rank": 7,
      "player": "Scottie Scheffler",
      "Avg": "68.00",
      "Total Strokes": "68",
      "Total Rounds": "1"
    },
    {
      "rank": 15,
      "player": "Emiliano Grillo",
      "Avg": "69.00",
      "Total Strokes": "69",
      "Total Rounds": "1"
    },
    {
      "rank": 15,
      "player": "Rory McIlroy",
      "Avg": "69.00",
      "Total Strokes": "69",
      "Total Rounds": "1"
    },
    {
      "rank": 15,
      "player": "J.T. Poston",
      "Avg": "69.00",
      "Total Strokes": "69",
      "Total Rounds": "1"
    },
    {
      "rank": 18,
      "player": "Wyndham Clark",
      "Avg": "70.00",
      "Total Strokes": "70",
      "Total Rounds": "1"
    },
    {
      "rank": 18,
      "player": "Taylor Moore",
      "Avg": "70.00",
      "Total Strokes": "70",
      "Total Rounds": "1"
    },
    {
      "rank": 18,
      "player": "Collin Morikawa",
      "Avg": "70.00",
      "Total Strokes": "70",
      "Total Rounds": "1"
    },
    {
      "rank": 18,
      "player": "C.T. Pan",
      "Avg": "70.00",
      "Total Strokes": "70",
      "Total Rounds": "1"
    },
    {
      "rank": 18,
      "player": "Sam Ryder",
      "Avg": "70.00",
      "Total Strokes": "70",
      "Total Rounds": "1"
    },
    {
      "rank": 18,
      "player": "Sepp Straka",
      "Avg": "70.00",
      "Total Strokes": "70",
      "Total Rounds": "1"
    },
    {
      "rank": 24,
      "player": "Jason Day",
      "Avg": "72.00",
      "Total Strokes": "72",
      "Total Rounds": "1"
    },
    {
      "rank": 24,
      "player": "Lee Hodges",
      "Avg": "72.00",
      "Total Strokes": "72",
      "Total Rounds": "1"
    },
    {
      "rank": 24,
      "player": "Mark Hubbard",
      "Avg": "72.00",
      "Total Strokes": "72",
      "Total Rounds": "1"
    },
    {
      "rank": 24,
      "player": "Matti Schmid",
      "Avg": "72.00",
      "Total Strokes": "72",
      "Total Rounds": "1"
    },
    {
      "rank": 28,
      "player": "Corey Conners",
      "Avg": "73.00",
      "Total Strokes": "73",
      "Total Rounds": "1"
    },
    {
      "rank": 28,
      "player": "Chris Kirk",
      "Avg": "73.00",
      "Total Strokes": "73",
      "Total Rounds": "1"
    },
    {
      "rank": 28,
      "player": "Ryan Moore",
      "Avg": "73.00",
      "Total Strokes": "73",
      "Total Rounds": "1"
    },
    {
      "rank": 28,
      "player": "Cameron Young",
      "Avg": "73.00",
      "Total Strokes": "73",
      "Total Rounds": "1"
    },
    {
      "rank": 32,
      "player": "Harris English",
      "Avg": "75.00",
      "Total Strokes": "75",
      "Total Rounds": "1"
    },
    {
      "rank": 32,
      "player": "Tom Hoge",
      "Avg": "75.00",
      "Total Strokes": "75",
      "Total Rounds": "1"
    },
    {
      "rank": 34,
      "player": "Keith Mitchell",
      "Avg": "76.00",
      "Total Strokes": "76",
      "Total Rounds": "1"
    },
    {
      "rank": 34,
      "player": "Nick Taylor",
      "Avg": "76.00",
      "Total Strokes": "76",
      "Total Rounds": "1"
    },
    {
      "rank": 36,
      "player": "Seamus Power",
      "Avg": "78.00",
      "Total Strokes": "78",
      "Total Rounds": "1"
    }
  ]
}