{
  "stat_id": "02378",
  "year": 2023,
  "category": "Approach the Green",
  "stat_title": "Approach 250-275 yards (RTP)",
  "rows": [
    {
      "rank": 1,
      "player": "Sung Kang",
      "Avg RTP": "-1.000"
    },
    {
      "rank": 2,
      "player": "Scott Piercy",
      "Avg RTP": "-.926"
    },
    {
      "rank": 3,
      "player": "Kevin Tway",
      "Avg RTP": "-.909"
    },
    {
      "rank": 4,
      "player": "Ludvig \u00c5berg",
      "Avg RTP": "-.857"
    },
    {
      "rank": 5,
      "player": "Adam Long",
      "Avg RTP": "-.844"
    },
    {
      "rank": 6,
      "player": "Thomas Detry",
      "Avg RTP": "-.824"
    },
    {
      "rank": 7,
      "player": "Zac Blair",
      "Avg RTP": "-.806"
    },
    {
      "rank": 8,
      "player": "Martin Trainer",
      "Avg RTP": "-.789"
    },
    {
      "rank": 9,
      "player": "Harry Higgs",
      "Avg RTP": "-.783"
    },
    {
      "rank": 10,
      "player": "Webb Simpson",
      "Avg RTP": "-.769"
    },
    {
      "rank": 11,
      "player": "Trey Mullinax",
      "Avg RTP": "-.760"
    },
    {
      "rank": 12,
      "player": "Stephan Jaeger",
      "Avg RTP": "-.756"
    },
    {
      "rank": 13,
      "player": "Jonathan Byrd",
      "Avg RTP": "-.750"
    },
    {
      "rank": 13,
      "player": "Kevin Yu",
      "Avg RTP": "-.750"
    },
    {
      "rank": 15,
      "player": "Erik van Rooyen",
      "Avg RTP": "-.741"
    },
    {
      "rank": 16,
      "player": "Jimmy Walker",
      "Avg RTP": "-.733"
    },
    {
      "rank": 17,
      "player": "Wesley Bryan",
      "Avg RTP": "-.727"
    },
    {
      "rank": 17,
      "player": "Zecheng Dou",
      "Avg RTP": "-.727"
    },
    {
      "rank": 19,
      "player": "Davis Thompson",
      "Avg RTP": "-.723"
    },
    {
      "rank": 20,
      "player": "Russell Knox",
      "Avg RTP": "-.714"
    },
    {
      "rank": 20,
      "player": "Nick Watney",
      "Avg RTP": "-.714"
    },
    {
      "rank": 22,
      "player": "Danny Willett",
      "Avg RTP": "-.708"
    },
    {
      "rank": 23,
      "player": "Brandon Wu",
      "Avg RTP": "-.707"
    },
    {
      "rank": 24,
      "player": "Chad Ramey",
      "Avg RTP": "-.702"
    },
    {
      "rank": 25,
      "player": "Augusto N\u00fa\u00f1ez",
      "Avg RTP": "-.700"
    },
    {
      "rank": 26,
      "player": "MJ Daffue",
      "Avg RTP": "-.697"
    },
    {
      "rank": 26,
      "player": "Jordan Spieth",
      "Avg RTP": "-.697"
    },
    {
      "rank": 28,
      "player": "Sungjae Im",
      "Avg RTP": "-.694"
    },
    {
      "rank": 29,
      "player": "Ryan Palmer",
      "Avg RTP": "-.692"
    },
    {
      "rank": 30,
      "player": "Patton Kizzire",
      "Avg RTP": "-.690"
    },
    {
      "rank": 31,
      "player": "Harrison Endycott",
      "Avg RTP": "-.686"
    },
    {
      "rank": 31,
      "player": "Scottie Scheffler",
      "Avg RTP": "-.686"
    },
    {
      "rank": 31,
      "player": "Adam Schenk",
      "Avg RTP": "-.686"
    },
    {
      "rank": 34,
      "player": "Kevin Chappell",
      "Avg RTP": "-.684"
    },
    {
      "rank": 34,
      "player": "Peter Kuest",
      "Avg RTP": "-.684"
    },
    {
      "rank": 34,
      "player": "Kevin Roy",
      "Avg RTP": "-.684"
    },
    {
      "rank": 37,
      "player": "Richy Werenski",
      "Avg RTP": "-.679"
    },
    {
      "rank": 38,
      "player": "Cam Davis",
      "Avg RTP": "-.676"
    },
    {
      "rank": 38,
      "player": "Carl Yuan",
      "Avg RTP": "-.676"
    },
    {
      "rank": 40,
      "player": "Garrick Higgo",
      "Avg RTP": "-.674"
    },
    {
      "rank": 41,
      "player": "Tyler Duncan",
      "Avg RTP": "-.667"
    },
    {
      "rank": 41,
      "player": "Dylan Frittelli",
      "Avg RTP": "-.667"
    },
    {
      "rank": 41,
      "player": "Brian Harman",
      "Avg RTP": "-.667"
    },
    {
      "rank": 41,
      "player": "Si Woo Kim",
      "Avg RTP": "-.667"
    },
    {
      "rank": 45,
      "player": "Beau Hossler",
      "Avg RTP": "-.639"
    },
    {
      "rank": 46,
      "player": "Kelly Kraft",
      "Avg RTP": "-.636"
    },
    {
      "rank": 46,
      "player": "Matt Wallace",
      "Avg RTP": "-.636"
    },
    {
      "rank": 48,
      "player": "Chesson Hadley",
      "Avg RTP": "-.634"
    },
    {
      "rank": 49,
      "player": "Jason Dufner",
      "Avg RTP": "-.633"
    },
    {
      "rank": 50,
      "player": "Collin Morikawa",
      "Avg RTP": "-.632"
    },
    {
      "rank": 50,
      "player": "Kevin Streelman",
      "Avg RTP": "-.632"
    },
    {
      "rank": 52,
      "player": "Chez Reavie",
      "Avg RTP": "-.630"
    },
    {
      "rank": 53,
      "player": "Tyson Alexander",
      "Avg RTP": "-.625"
    },
    {
      "rank": 54,
      "player": "Lee Hodges",
      "Avg RTP": "-.623"
    },
    {
      "rank": 55,
      "player": "Mark Hubbard",
      "Avg RTP": "-.622"
    },
    {
      "rank": 55,
      "player": "Justin Suh",
      "Avg RTP": "-.622"
    },
    {
      "rank": 57,
      "player": "Nate Lashley",
      "Avg RTP": "-.618"
    },
    {
      "rank": 57,
      "player": "Dylan Wu",
      "Avg RTP": "-.618"
    },
    {
      "rank": 59,
      "player": "Austin Smotherman",
      "Avg RTP": "-.614"
    },
    {
      "rank": 60,
      "player": "Tony Finau",
      "Avg RTP": "-.613"
    },
    {
      "rank": 61,
      "player": "Satoshi Kodaira",
      "Avg RTP": "-.611"
    },
    {
      "rank": 61,
      "player": "S.Y. Noh",
      "Avg RTP": "-.611"
    },
    {
      "rank": 63,
      "player": "Adam Svensson",
      "Avg RTP": "-.607"
    },
    {
      "rank": 64,
      "player": "Ben Griffin",
      "Avg RTP": "-.605"
    },
    {
      "rank": 65,
      "player": "Cameron Champ",
      "Avg RTP": "-.600"
    },
    {
      "rank": 65,
      "player": "Sepp Straka",
      "Avg RTP": "-.600"
    },
    {
      "rank": 65,
      "player": "Kyle Westmoreland",
      "Avg RTP": "-.600"
    },
    {
      "rank": 68,
      "player": "Alex Smalley",
      "Avg RTP": "-.595"
    },
    {
      "rank": 69,
      "player": "C.T. Pan",
      "Avg RTP": "-.588"
    },
    {
      "rank": 70,
      "player": "Aaron Rai",
      "Avg RTP": "-.587"
    },
    {
      "rank": 71,
      "player": "Harry Hall",
      "Avg RTP": "-.586"
    },
    {
      "rank": 72,
      "player": "Sean O'Hair",
      "Avg RTP": "-.583"
    },
    {
      "rank": 73,
      "player": "Matt Kuchar",
      "Avg RTP": "-.579"
    },
    {
      "rank": 74,
      "player": "Jon Rahm",
      "Avg RTP": "-.577"
    },
    {
      "rank": 75,
      "player": "Taylor Pendrith",
      "Avg RTP": "-.571"
    },
    {
      "rank": 75,
      "player": "Greyson Sigg",
      "Avg RTP": "-.571"
    },
    {
      "rank": 77,
      "player": "David Lipsky",
      "Avg RTP": "-.567"
    },
    {
      "rank": 77,
      "player": "Peter Malnati",
      "Avg RTP": "-.567"
    },
    {
      "rank": 79,
      "player": "Christiaan Bezuidenhout",
      "Avg RTP": "-.563"
    },
    {
      "rank": 79,
      "player": "K.H. Lee",
      "Avg RTP": "-.563"
    },
    {
      "rank": 81,
      "player": "Ryan Gerard",
      "Avg RTP": "-.560"
    },
    {
      "rank": 81,
      "player": "Charley Hoffman",
      "Avg RTP": "-.560"
    },
    {
      "rank": 83,
      "player": "Brandon Matthews",
      "Avg RTP": "-.556"
    },
    {
      "rank": 83,
      "player": "Max McGreevy",
      "Avg RTP": "-.556"
    },
    {
      "rank": 83,
      "player": "Andrew Putnam",
      "Avg RTP": "-.556"
    },
    {
      "rank": 86,
      "player": "Justin Lower",
      "Avg RTP": "-.553"
    },
    {
      "rank": 87,
      "player": "David Lingmerth",
      "Avg RTP": "-.550"
    },
    {
      "rank": 87,
      "player": "Maverick McNealy",
      "Avg RTP": "-.550"
    },
    {
      "rank": 87,
      "player": "Robby Shelton",
      "Avg RTP": "-.550"
    },
    {
      "rank": 90,
      "player": "Cameron Percy",
      "Avg RTP": "-.545"
    },
    {
      "rank": 90,
      "player": "Matti Schmid",
      "Avg RTP": "-.545"
    },
    {
      "rank": 92,
      "player": "Robert Streb",
      "Avg RTP": "-.542"
    },
    {
      "rank": 93,
      "player": "Brice Garnett",
      "Avg RTP": "-.538"
    },
    {
      "rank": 94,
      "player": "Vincent Norrman",
      "Avg RTP": "-.536"
    },
    {
      "rank": 95,
      "player": "Sam Burns",
      "Avg RTP": "-.535"
    },
    {
      "rank": 96,
      "player": "Scott Stallings",
      "Avg RTP": "-.533"
    },
    {
      "rank": 97,
      "player": "Akshay Bhatia",
      "Avg RTP": "-.531"
    },
    {
      "rank": 97,
      "player": "Austin Eckroat",
      "Avg RTP": "-.531"
    },
    {
      "rank": 97,
      "player": "Troy Merritt",
      "Avg RTP": "-.531"
    },
    {
      "rank": 100,
      "player": "Kramer Hickok",
      "Avg RTP": "-.529"
    },
    {
      "rank": 101,
      "player": "Brendon Todd",
      "Avg RTP": "-.528"
    },
    {
      "rank": 102,
      "player": "Taylor Montgomery",
      "Avg RTP": "-.524"
    },
    {
      "rank": 103,
      "player": "Doug Ghim",
      "Avg RTP": "-.523"
    },
    {
      "rank": 104,
      "player": "Eric Cole",
      "Avg RTP": "-.522"
    },
    {
      "rank": 105,
      "player": "Scott Harrington",
      "Avg RTP": "-.517"
    },
    {
      "rank": 105,
      "player": "Andrew Novak",
      "Avg RTP": "-.517"
    },
    {
      "rank": 107,
      "player": "Lucas Glover",
      "Avg RTP": "-.515"
    },
    {
      "rank": 107,
      "player": "Justin Thomas",
      "Avg RTP": "-.515"
    },
    {
      "rank": 109,
      "player": "Carson Young",
      "Avg RTP": "-.514"
    },
    {
      "rank": 110,
      "player": "Denny McCarthy",
      "Avg RTP": "-.513"
    },
    {
      "rank": 111,
      "player": "Tommy Fleetwood",
      "Avg RTP": "-.512"
    },
    {
      "rank": 111,
      "player": "Chris Kirk",
      "Avg RTP": "-.512"
    },
    {
      "rank": 113,
      "player": "Rickie Fowler",
      "Avg RTP": "-.511"
    },
    {
      "rank": 114,
      "player": "Keegan Bradley",
      "Avg RTP": "-.500"
    },
    {
      "rank": 114,
      "player": "Joseph Bramlett",
      "Avg RTP": "-.500"
    },
    {
      "rank": 114,
      "player": "Wyndham Clark",
      "Avg RTP": "-.500"
    },
    {
      "rank": 114,
      "player": "Michael Gligic",
      "Avg RTP": "-.500"
    },
    {
      "rank": 114,
      "player": "Mackenzie Hughes",
      "Avg RTP": "-.500"
    },
    {
      "rank": 119,
      "player": "Matt Fitzpatrick",
      "Avg RTP": "-.488"
    },
    {
      "rank": 120,
      "player": "James Hahn",
      "Avg RTP": "-.484"
    },
    {
      "rank": 120,
      "player": "Ryan Moore",
      "Avg RTP": "-.484"
    },
    {
      "rank": 122,
      "player": "Ben Taylor",
      "Avg RTP": "-.481"
    },
    {
      "rank": 123,
      "player": "Hank Lebioda",
      "Avg RTP": "-.478"
    },
    {
      "rank": 123,
      "player": "Justin Rose",
      "Avg RTP": "-.478"
    },
    {
      "rank": 125,
      "player": "Tom Hoge",
      "Avg RTP": "-.477"
    },
    {
      "rank": 125,
      "player": "S.H. Kim",
      "Avg RTP": "-.477"
    },
    {
      "rank": 127,
      "player": "Paul Haley II",
      "Avg RTP": "-.476"
    },
    {
      "rank": 128,
      "player": "Andrew Landry",
      "Avg RTP": "-.474"
    },
    {
      "rank": 128,
      "player": "Chris Stroud",
      "Avg RTP": "-.474"
    },
    {
      "rank": 130,
      "player": "Matthias Schwab",
      "Avg RTP": "-.472"
    },
    {
      "rank": 130,
      "player": "J.J. Spaun",
      "Avg RTP": "-.472"
    },
    {
      "rank": 132,
      "player": "Shane Lowry",
      "Avg RTP": "-.471"
    },
    {
      "rank": 132,
      "player": "Patrick Rodgers",
      "Avg RTP": "-.471"
    },
    {
      "rank": 134,
      "player": "Sam Stevens",
      "Avg RTP": "-.467"
    },
    {
      "rank": 135,
      "player": "Harris English",
      "Avg RTP": "-.462"
    },
    {
      "rank": 135,
      "player": "Cody Gribble",
      "Avg RTP": "-.462"
    },
    {
      "rank": 135,
      "player": "Sam Ryder",
      "Avg RTP": "-.462"
    },
    {
      "rank": 138,
      "player": "Corey Conners",
      "Avg RTP": "-.459"
    },
    {
      "rank": 139,
      "player": "Doc Redman",
      "Avg RTP": "-.458"
    },
    {
      "rank": 140,
      "player": "Ben Martin",
      "Avg RTP": "-.457"
    },
    {
      "rank": 141,
      "player": "Davis Riley",
      "Avg RTP": "-.455"
    },
    {
      "rank": 142,
      "player": "Tom Kim",
      "Avg RTP": "-.452"
    },
    {
      "rank": 142,
      "player": "Martin Laird",
      "Avg RTP": "-.452"
    },
    {
      "rank": 144,
      "player": "Emiliano Grillo",
      "Avg RTP": "-.451"
    },
    {
      "rank": 145,
      "player": "Patrick Cantlay",
      "Avg RTP": "-.447"
    },
    {
      "rank": 146,
      "player": "Nicolai Hojgaard",
      "Avg RTP": "-.444"
    },
    {
      "rank": 146,
      "player": "Cameron Young",
      "Avg RTP": "-.444"
    },
    {
      "rank": 148,
      "player": "Xander Schauffele",
      "Avg RTP": "-.441"
    },
    {
      "rank": 149,
      "player": "Henrik Norlander",
      "Avg RTP": "-.435"
    },
    {
      "rank": 149,
      "player": "Trevor Werbylo",
      "Avg RTP": "-.435"
    },
    {
      "rank": 151,
      "player": "Joel Dahmen",
      "Avg RTP": "-.433"
    },
    {
      "rank": 152,
      "player": "Byeong Hun An",
      "Avg RTP": "-.429"
    },
    {
      "rank": 152,
      "player": "Tano Goya",
      "Avg RTP": "-.429"
    },
    {
      "rank": 154,
      "player": "Matt NeSmith",
      "Avg RTP": "-.424"
    },
    {
      "rank": 155,
      "player": "Stewart Cink",
      "Avg RTP": "-.423"
    },
    {
      "rank": 156,
      "player": "Aaron Baddeley",
      "Avg RTP": "-.409"
    },
    {
      "rank": 157,
      "player": "Adam Hadwin",
      "Avg RTP": "-.408"
    },
    {
      "rank": 158,
      "player": "Rory McIlroy",
      "Avg RTP": "-.407"
    },
    {
      "rank": 159,
      "player": "Will Gordon",
      "Avg RTP": "-.405"
    },
    {
      "rank": 160,
      "player": "Alex Noren",
      "Avg RTP": "-.400"
    },
    {
      "rank": 161,
      "player": "Zach Johnson",
      "Avg RTP": "-.393"
    },
    {
      "rank": 162,
      "player": "Lucas Herbert",
      "Avg RTP": "-.391"
    },
    {
      "rank": 163,
      "player": "Tyrrell Hatton",
      "Avg RTP": "-.385"
    },
    {
      "rank": 163,
      "player": "Michael Kim",
      "Avg RTP": "-.385"
    },
    {
      "rank": 163,
      "player": "William McGirt",
      "Avg RTP": "-.385"
    },
    {
      "rank": 166,
      "player": "J.T. Poston",
      "Avg RTP": "-.378"
    },
    {
      "rank": 167,
      "player": "Nick Hardy",
      "Avg RTP": "-.373"
    },
    {
      "rank": 168,
      "player": "Jim Herman",
      "Avg RTP": "-.364"
    },
    {
      "rank": 169,
      "player": "Sahith Theegala",
      "Avg RTP": "-.361"
    },
    {
      "rank": 169,
      "player": "Gary Woodland",
      "Avg RTP": "-.361"
    },
    {
      "rank": 171,
      "player": "Nick Taylor",
      "Avg RTP": "-.357"
    },
    {
      "rank": 172,
      "player": "Brent Grant",
      "Avg RTP": "-.355"
    },
    {
      "rank": 173,
      "player": "Max Homa",
      "Avg RTP": "-.353"
    },
    {
      "rank": 174,
      "player": "Viktor Hovland",
      "Avg RTP": "-.351"
    },
    {
      "rank": 175,
      "player": "Ryan Brehm",
      "Avg RTP": "-.350"
    },
    {
      "rank": 176,
      "player": "Lanto Griffin",
      "Avg RTP": "-.346"
    },
    {
      "rank": 177,
      "player": "Russell Henley",
      "Avg RTP": "-.342"
    },
    {
      "rank": 178,
      "player": "Jason Day",
      "Avg RTP": "-.333"
    },
    {
      "rank": 178,
      "player": "Luke List",
      "Avg RTP": "-.333"
    },
    {
      "rank": 180,
      "player": "Seamus Power",
      "Avg RTP": "-.324"
    },
    {
      "rank": 181,
      "player": "Hideki Matsuyama",
      "Avg RTP": "-.314"
    },
    {
      "rank": 182,
      "player": "Taylor Moore",
      "Avg RTP": "-.313"
    },
    {
      "rank": 183,
      "player": "Nico Echavarria",
      "Avg RTP": "-.308"
    },
    {
      "rank": 184,
      "player": "Ryan Armour",
      "Avg RTP": "-.286"
    },
    {
      "rank": 184,
      "player": "Brian Stuard",
      "Avg RTP": "-.286"
    },
    {
      "rank": 186,
      "player": "Keith Mitchell",
      "Avg RTP": "-.281"
    },
    {
      "rank": 187,
      "player": "Trevor Cone",
      "Avg RTP": "-.229"
    },
    {
      "rank": 188,
      "player": "Hayden Buckley",
      "Avg RTP": "-.212"
    },
    {
      "rank": 189,
      "player": "Kurt Kitayama",
      "Avg RTP": "-.211"
    },
    {
      "rank": 190,
      "player": "Billy Horschel",
      "Avg RTP": "-.200"
    },
    {
      "rank": 191,
      "player": "Austin Cook",
      "Avg RTP": "-.188"
    },
    {
      "rank": 192,
      "player": "Callum Tarren",
      "Avg RTP": "-.043"
    },
    {
      "rank": 193,
      "player": "Adam Scott",
      "Avg RTP": "E"
    }
  ]
}